h2md/__init__.py
h2md/__main__.py
h2md/convert.py
h2md/test_convert.py
h2md-1.0.3.dist-info/LICENSE
h2md-1.0.3.dist-info/METADATA
h2md-1.0.3.dist-info/WHEEL
h2md-1.0.3.dist-info/entry_points.txt
h2md-1.0.3.dist-info/top_level.txt
h2md-1.0.3.dist-info/RECORD
