Metadata-Version: 2.1
Name: h2md
Version: 1.0.3
Summary: This will convert the content part of html into a markdown file.
Home-page: https://github.com/canovie/h2md
Author: Jerry Chan（陈家俊）
Author-email: jerry@mydream.ink
License: UNKNOWN
Platform: UNKNOWN
Classifier: Programming Language :: Python :: 3
Classifier: License :: OSI Approved :: Apache Software License
Classifier: Operating System :: OS Independent
Requires-Dist: bs4
